fastapi_appattest/__init__.py
fastapi_appattest/config.py
fastapi_appattest/fastapi_appattest.py
fastapi_appattest/middleware.py
fastapi_appattest/py.typed
fastapi_appattest/schema.py
fastapi_appattest-0.1.0.dist-info/LICENSE
fastapi_appattest-0.1.0.dist-info/METADATA
fastapi_appattest-0.1.0.dist-info/WHEEL
fastapi_appattest-0.1.0.dist-info/RECORD
