Metadata-Version: 2.3
Name: fastapi-appattest
Version: 0.1.0
Summary: FastAPI extension that provides App Attest support (secure, easy to use, and lightweight)
License: MIT
Keywords: fastapi,api,security,Apple,iOS,device-attestation
Author: Piyush Raj
Author-email: hello@piyushraj.org
Requires-Python: >=3.8,<4.0
Classifier: Framework :: FastAPI
Classifier: License :: OSI Approved :: MIT License
Classifier: Operating System :: OS Independent
Classifier: Programming Language :: Python :: 3
Classifier: Programming Language :: Python :: 3.8
Classifier: Programming Language :: Python :: 3.9
Classifier: Programming Language :: Python :: 3.10
Classifier: Programming Language :: Python :: 3.11
Classifier: Programming Language :: Python :: 3.12
Classifier: Programming Language :: Python :: 3.13
Classifier: Topic :: Security
Classifier: Topic :: Software Development :: Libraries :: Application Frameworks
Requires-Dist: fastapi (==0.108.0)
Requires-Dist: httpx (==0.28.1)
Requires-Dist: pydantic (==2.10.6)
Requires-Dist: pydantic-settings (==2.8.1)
Requires-Dist: python-jose (==3.4.0)
Project-URL: Homepage, https://github.com/0x48piraj/fastapi-appattest
Project-URL: Repository, https://github.com/0x48piraj/fastapi-appattest
